pictorus/__init__.py
pictorus/command.py
pictorus/config.py
pictorus/constants.py
pictorus/date_utils.py
pictorus/device_manager.py
pictorus/exceptions.py
pictorus/logging_utils.py
pictorus/pictorus_cli.py
pictorus/pictorus_device_manager.py
pictorus/systemd.py
pictorus/types.py
pictorus/updates_manager.py
pictorus/comms/comms_handler.py
pictorus/comms/data_queue.py
pictorus/comms/mqtt_comms_handler.py
pictorus/comms/streaming_comms_handler.py
pictorus/comms/webrtc_comms_handler.py
pictorus/daemons/__init__.py
pictorus/daemons/daemon.py
pictorus/daemons/launchd.py
pictorus/daemons/sudosystemd.py
pictorus/daemons/systemd.py
pictorus/daemons/utils.py
pictorus/postcard/README.md
pictorus/postcard/__init__.py
pictorus/postcard/deserialize/README.md
pictorus/postcard/deserialize/__init__.py
pictorus/postcard/deserialize/array.py
pictorus/postcard/deserialize/core.py
pictorus/postcard/deserialize/float.py
pictorus/postcard/deserialize/option.py
pictorus/postcard/deserialize/string.py
pictorus/postcard/deserialize/varint.py
pictorus/postcard/deserialize/vec.py
pictorus/postcard/schema/README.md
pictorus/postcard/schema/__init__.py
pictorus/postcard/schema/core.py
pictorus/postcard/schema/json.py
pictorus/target_manager/__init__.py
pictorus/target_manager/embedded_target_manager.py
pictorus/target_manager/proc_target_manager.py
pictorus/target_manager/target_manager.py
pictorus-0.6.0.dist-info/entry_points.txt
pictorus-0.6.0.dist-info/licenses/LICENSE
pictorus-0.6.0.dist-info/WHEEL
pictorus-0.6.0.dist-info/METADATA
pictorus-0.6.0.dist-info/RECORD
