Metadata-Version: 2.4
Name: pictorus
Version: 0.6.0
Summary: Pictorus device manager package
Author-email: Pictorus Inc <contact@pictor.us>
Requires-Python: >=3.10
Classifier: License :: OSI Approved :: GNU General Public License v3 or later (GPLv3+)
License-File: LICENSE
Requires-Dist: awsiotsdk~=1.19.0
Requires-Dist: requests~=2.31.0
Requires-Dist: pyocd~=0.36.0
Requires-Dist: python-jose~=3.3.0
Requires-Dist: semver~=2.13.0
Requires-Dist: backports-datetime-fromisoformat; python_version <= "3.12"
Requires-Dist: psutil~=7.0.0
Requires-Dist: cobs~=1.2.1
Requires-Dist: cbor2~=5.6.5
Requires-Dist: aiortc~=1.14.0
Requires-Dist: pre-commit==3.6.0 ; extra == "dev"
Requires-Dist: black==22.3.0 ; extra == "dev"
Requires-Dist: flake8==7.0.0 ; extra == "dev"
Requires-Dist: pyright==1.1.402 ; extra == "dev"
Requires-Dist: responses==0.17.0 ; extra == "test"
Requires-Dist: pytest==9.0.2 ; extra == "test"
Requires-Dist: cryptography>=40.0.2 ; extra == "test"
Requires-Dist: syrupy ; extra == "test"
Project-URL: Home, https://pictor.us
Provides-Extra: dev
Provides-Extra: test
